{
	"customers":[
  {
    "name": "Twila Walton",
    "city": "COMDOM",
    "joined": "2014-03-24T03:27:13 +05:00"
  },
  {
    "name": "Evans Kim",
    "city": "FANGOLD",
    "joined": "2015-04-19T04:56:49 +05:00"
  },
  {
    "name": "Caldwell Snow",
    "city": "TERSANKI",
    "joined": "2014-03-12T06:24:00 +05:00"
  },
  {
    "name": "Mavis Cabrera",
    "city": "LIQUICOM",
    "joined": "2015-02-25T12:57:07 +05:00"
  },
  {
    "name": "Kane Smith",
    "city": "NETILITY",
    "joined": "2014-11-12T05:30:44 +05:00"
  },
  {
    "name": "Peck Dyer",
    "city": "ROCKYARD",
    "joined": "2014-08-14T06:23:59 +05:00"
  },
  {
    "name": "Finley Rosales",
    "city": "PATHWAYS",
    "joined": "2015-06-17T07:58:48 +05:00"
  },
  {
    "name": "Iris Mcintyre",
    "city": "ORBALIX",
    "joined": "2015-06-19T06:30:43 +05:00"
  },
  {
    "name": "Velasquez Hatfield",
    "city": "BRAINQUIL",
    "joined": "2014-12-30T03:57:51 +05:00"
  },
  {
    "name": "Barber Keller",
    "city": "HOMETOWN",
    "joined": "2014-11-05T05:48:48 +05:00"
  },
  {
    "name": "Christi Meadows",
    "city": "COGNICODE",
    "joined": "2015-07-31T02:08:41 +05:00"
  },
  {
    "name": "Cotton Odom",
    "city": "ENTROFLEX",
    "joined": "2014-04-20T05:38:17 +05:00"
  },
  {
    "name": "Burris Zimmerman",
    "city": "CORPORANA",
    "joined": "2014-09-06T05:29:48 +05:00"
  },
  {
    "name": "Brianna Mcintosh",
    "city": "GOLISTIC",
    "joined": "2015-07-07T11:12:18 +05:00"
  },
  {
    "name": "Baird Prince",
    "city": "SPHERIX",
    "joined": "2014-04-01T08:00:37 +05:00"
  },
  {
    "name": "Perry Spears",
    "city": "ACUSAGE",
    "joined": "2014-06-24T08:36:30 +05:00"
  },
  {
    "name": "Lori Flynn",
    "city": "INCUBUS",
    "joined": "2014-04-27T08:07:01 +05:00"
  },
  {
    "name": "Yang Pena",
    "city": "PORTALIS",
    "joined": "2014-06-28T09:22:42 +05:00"
  },
  {
    "name": "Rosetta Bolton",
    "city": "EGYPTO",
    "joined": "2015-06-04T09:45:57 +05:00"
  },
  {
    "name": "Hurst Knight",
    "city": "PERKLE",
    "joined": "2015-07-24T05:36:00 +05:00"
  },
  {
    "name": "Reyna Blevins",
    "city": "GROK",
    "joined": "2014-08-12T12:30:27 +05:00"
  },
  {
    "name": "Imelda Love",
    "city": "SENMAO",
    "joined": "2014-03-14T10:56:53 +05:00"
  },
  {
    "name": "Dalton Klein",
    "city": "HAIRPORT",
    "joined": "2015-08-27T11:57:01 +05:00"
  },
  {
    "name": "Jacquelyn Shelton",
    "city": "PHORMULA",
    "joined": "2015-02-08T12:29:12 +05:00"
  },
  {
    "name": "Velez Cooke",
    "city": "PETICULAR",
    "joined": "2015-02-09T10:12:05 +05:00"
  },
  {
    "name": "Carmella Waller",
    "city": "NIXELT",
    "joined": "2014-01-27T04:55:44 +05:00"
  },
  {
    "name": "Joseph Coleman",
    "city": "AFFLUEX",
    "joined": "2015-02-24T06:25:09 +05:00"
  },
  {
    "name": "Maddox Logan",
    "city": "CONJURICA",
    "joined": "2015-01-30T06:15:39 +05:00"
  },
  {
    "name": "Key Solis",
    "city": "PROSURE",
    "joined": "2014-01-30T12:26:26 +05:00"
  },
  {
    "name": "Rosalinda Oneal",
    "city": "FUELWORKS",
    "joined": "2015-03-11T04:19:27 +05:00"
  },
  {
    "name": "Kenya Velasquez",
    "city": "ZAYA",
    "joined": "2015-04-17T04:41:14 +05:00"
  },
  {
    "name": "Moon Gibbs",
    "city": "ZENOLUX",
    "joined": "2015-07-07T09:46:11 +05:00"
  },
  {
    "name": "Sharlene Buckley",
    "city": "ZIORE",
    "joined": "2015-04-26T01:20:19 +05:00"
  },
  {
    "name": "Gordon Compton",
    "city": "ZOARERE",
    "joined": "2015-08-27T05:23:03 +05:00"
  },
  {
    "name": "Nelda Phillips",
    "city": "UNCORP",
    "joined": "2014-05-20T07:41:16 +05:00"
  },
  {
    "name": "Mccarty Gentry",
    "city": "STRALUM",
    "joined": "2015-04-13T01:01:42 +05:00"
  },
  {
    "name": "Casandra Jensen",
    "city": "METROZ",
    "joined": "2014-05-01T12:37:26 +05:00"
  },
  {
    "name": "James Mcbride",
    "city": "CORMORAN",
    "joined": "2014-04-25T02:40:31 +05:00"
  },
  {
    "name": "Cathy Reed",
    "city": "QUALITEX",
    "joined": "2014-07-30T09:10:36 +05:00"
  },
  {
    "name": "Mandy Bailey",
    "city": "RUGSTARS",
    "joined": "2014-03-23T12:49:55 +05:00"
  },
  {
    "name": "Nielsen Carver",
    "city": "DANCERITY",
    "joined": "2015-02-09T01:01:41 +05:00"
  },
  {
    "name": "Olsen Reeves",
    "city": "FREAKIN",
    "joined": "2015-01-14T01:08:00 +05:00"
  },
  {
    "name": "Chaney Stevenson",
    "city": "CORPULSE",
    "joined": "2014-07-05T10:52:07 +05:00"
  },
  {
    "name": "Lakisha Reynolds",
    "city": "VALREDA",
    "joined": "2014-08-20T07:29:50 +05:00"
  },
  {
    "name": "Beard Castaneda",
    "city": "ZIGGLES",
    "joined": "2015-07-04T01:34:17 +05:00"
  },
  {
    "name": "Antoinette Hull",
    "city": "RAMJOB",
    "joined": "2014-01-05T12:59:57 +05:00"
  },
  {
    "name": "Eula Ford",
    "city": "VERTON",
    "joined": "2014-04-10T08:23:23 +05:00"
  },
  {
    "name": "Leah Romero",
    "city": "TYPHONICA",
    "joined": "2015-03-29T05:24:29 +05:00"
  },
  {
    "name": "Gutierrez Bates",
    "city": "SHOPABOUT",
    "joined": "2015-07-22T08:56:33 +05:00"
  },
  {
    "name": "Rodriguez Garner",
    "city": "AMTAP",
    "joined": "2014-04-20T07:02:46 +05:00"
  },
  {
    "name": "Bullock Mathews",
    "city": "MAGMINA",
    "joined": "2014-04-13T04:26:19 +05:00"
  },
  {
    "name": "Taylor Harrell",
    "city": "DOGNOST",
    "joined": "2014-08-11T10:57:03 +05:00"
  },
  {
    "name": "Terrell Higgins",
    "city": "NURPLEX",
    "joined": "2015-08-19T02:38:41 +05:00"
  },
  {
    "name": "Rosanna Winters",
    "city": "CUBICIDE",
    "joined": "2014-07-01T11:44:59 +05:00"
  },
  {
    "name": "Virginia Carey",
    "city": "EMOLTRA",
    "joined": "2014-06-04T08:27:58 +05:00"
  },
  {
    "name": "Marianne Owen",
    "city": "REVERSUS",
    "joined": "2014-12-11T10:19:55 +05:00"
  },
  {
    "name": "Charles Valdez",
    "city": "ECRATIC",
    "joined": "2014-03-14T07:50:34 +05:00"
  },
  {
    "name": "Johanna Cunningham",
    "city": "IMANT",
    "joined": "2014-02-01T01:27:31 +05:00"
  },
  {
    "name": "Walker Brady",
    "city": "FIBEROX",
    "joined": "2014-04-15T07:37:10 +05:00"
  },
  {
    "name": "Kellie Horne",
    "city": "HAWKSTER",
    "joined": "2014-11-03T03:09:38 +05:00"
  },
  {
    "name": "Cole Bond",
    "city": "VITRICOMP",
    "joined": "2014-03-16T03:51:29 +05:00"
  },
  {
    "name": "Mayer Underwood",
    "city": "SPEEDBOLT",
    "joined": "2014-01-09T11:01:32 +05:00"
  },
  {
    "name": "Caitlin Contreras",
    "city": "ENTALITY",
    "joined": "2014-03-02T07:11:37 +05:00"
  },
  {
    "name": "Alma Levy",
    "city": "EXOSTREAM",
    "joined": "2015-03-30T12:10:28 +05:00"
  },
  {
    "name": "Rosales Williamson",
    "city": "KATAKANA",
    "joined": "2014-03-11T01:05:17 +05:00"
  },
  {
    "name": "Merle Harvey",
    "city": "PRISMATIC",
    "joined": "2015-03-14T04:59:38 +05:00"
  },
  {
    "name": "Nichols Beach",
    "city": "ZILLIDIUM",
    "joined": "2014-10-22T09:46:11 +05:00"
  },
  {
    "name": "Bowen Hebert",
    "city": "MYOPIUM",
    "joined": "2015-05-23T10:21:11 +05:00"
  },
  {
    "name": "Cabrera Carroll",
    "city": "PHOTOBIN",
    "joined": "2014-01-22T02:24:25 +05:00"
  },
  {
    "name": "Sheena Hodges",
    "city": "ZENTIX",
    "joined": "2014-09-01T11:35:46 +05:00"
  },
  {
    "name": "Hutchinson Cochran",
    "city": "OHMNET",
    "joined": "2014-11-25T09:18:34 +05:00"
  },
  {
    "name": "Dominique Petersen",
    "city": "ISOSURE",
    "joined": "2014-08-23T07:39:06 +05:00"
  },
  {
    "name": "Randi Barr",
    "city": "NETBOOK",
    "joined": "2014-12-23T09:14:58 +05:00"
  },
  {
    "name": "Judith Maxwell",
    "city": "HANDSHAKE",
    "joined": "2015-06-24T06:55:13 +05:00"
  },
  {
    "name": "Barrett Madden",
    "city": "SOFTMICRO",
    "joined": "2014-02-28T08:23:10 +05:00"
  },
  {
    "name": "Whitney Clements",
    "city": "NEXGENE",
    "joined": "2014-05-30T07:55:34 +05:00"
  },
  {
    "name": "Lancaster Brown",
    "city": "PLEXIA",
    "joined": "2015-01-01T10:06:14 +05:00"
  },
  {
    "name": "Isabella Rhodes",
    "city": "ISOSWITCH",
    "joined": "2014-07-20T04:22:20 +05:00"
  },
  {
    "name": "Bond Hopper",
    "city": "FANFARE",
    "joined": "2014-06-12T04:54:58 +05:00"
  },
  {
    "name": "Sandoval Martinez",
    "city": "TWIGGERY",
    "joined": "2014-05-03T06:25:34 +05:00"
  },
  {
    "name": "Hudson Doyle",
    "city": "DYNO",
    "joined": "2014-12-29T03:00:20 +05:00"
  },
  {
    "name": "Garza Glover",
    "city": "GAZAK",
    "joined": "2014-06-05T11:23:45 +05:00"
  },
  {
    "name": "Cleveland Mcfarland",
    "city": "GEOSTELE",
    "joined": "2015-03-06T11:22:57 +05:00"
  },
  {
    "name": "Adela Wolfe",
    "city": "QIAO",
    "joined": "2015-07-28T10:12:05 +05:00"
  },
  {
    "name": "Ferrell Berry",
    "city": "OLYMPIX",
    "joined": "2014-10-04T06:05:00 +05:00"
  },
  {
    "name": "Mcdonald Alvarez",
    "city": "XPLOR",
    "joined": "2015-01-02T06:47:45 +05:00"
  },
  {
    "name": "Rae Glenn",
    "city": "OBONES",
    "joined": "2015-02-20T01:45:08 +05:00"
  },
  {
    "name": "Jacobs Walsh",
    "city": "MATRIXITY",
    "joined": "2014-08-10T01:41:05 +05:00"
  },
  {
    "name": "Little Woodard",
    "city": "EXOBLUE",
    "joined": "2014-06-21T05:21:54 +05:00"
  },
  {
    "name": "Georgette Summers",
    "city": "MAGNAFONE",
    "joined": "2015-01-17T01:50:32 +05:00"
  },
  {
    "name": "Leticia Bishop",
    "city": "PYRAMIS",
    "joined": "2014-04-27T03:59:58 +05:00"
  },
  {
    "name": "Fletcher Holcomb",
    "city": "UTARIAN",
    "joined": "2015-07-06T07:53:19 +05:00"
  },
  {
    "name": "Ladonna Ryan",
    "city": "SKYPLEX",
    "joined": "2014-10-14T04:12:14 +05:00"
  },
  {
    "name": "Gregory Price",
    "city": "CENTREGY",
    "joined": "2014-12-11T02:31:11 +05:00"
  },
  {
    "name": "Russo Torres",
    "city": "NORALI",
    "joined": "2015-02-01T02:14:30 +05:00"
  },
  {
    "name": "Kemp Strong",
    "city": "PARCOE",
    "joined": "2014-01-21T04:36:44 +05:00"
  },
  {
    "name": "Vivian Parrish",
    "city": "LIMOZEN",
    "joined": "2015-06-08T09:53:24 +05:00"
  },
  {
    "name": "Marcia Chapman",
    "city": "GREEKER",
    "joined": "2014-04-04T02:39:05 +05:00"
  },
  {
    "name": "Wells Kelly",
    "city": "ACCEL",
    "joined": "2015-01-09T01:35:27 +05:00"
  },
  {
    "name": "Patterson Baker",
    "city": "GEEKOSIS",
    "joined": "2014-12-16T03:03:20 +05:00"
  },
  {
    "name": "Lucille Snyder",
    "city": "SHEPARD",
    "joined": "2015-07-25T12:01:09 +05:00"
  },
  {
    "name": "Roxanne Wiggins",
    "city": "GRUPOLI",
    "joined": "2015-07-30T08:04:30 +05:00"
  },
  {
    "name": "Delaney Jackson",
    "city": "SINGAVERA",
    "joined": "2015-05-12T01:53:52 +05:00"
  },
  {
    "name": "Whitfield Hurley",
    "city": "FURNIGEER",
    "joined": "2014-07-27T11:53:20 +05:00"
  },
  {
    "name": "Kristen Roy",
    "city": "ARCTIQ",
    "joined": "2014-06-22T08:58:41 +05:00"
  },
  {
    "name": "Shelley Santos",
    "city": "ADORNICA",
    "joined": "2015-04-16T09:51:49 +05:00"
  },
  {
    "name": "Higgins Carson",
    "city": "SARASONIC",
    "joined": "2014-01-30T06:15:58 +05:00"
  },
  {
    "name": "Maryanne Ware",
    "city": "UNISURE",
    "joined": "2014-12-05T04:33:43 +05:00"
  },
  {
    "name": "Puckett Bray",
    "city": "ZILIDIUM",
    "joined": "2014-05-05T03:12:03 +05:00"
  },
  {
    "name": "Lynch Rush",
    "city": "ROCKABYE",
    "joined": "2015-08-22T08:08:11 +05:00"
  },
  {
    "name": "Theresa Harding",
    "city": "UNDERTAP",
    "joined": "2014-10-14T03:40:19 +05:00"
  },
  {
    "name": "Young Fuller",
    "city": "CINESANCT",
    "joined": "2014-12-30T06:57:44 +05:00"
  },
  {
    "name": "Kari Cooper",
    "city": "EYEWAX",
    "joined": "2014-04-27T03:05:03 +05:00"
  },
  {
    "name": "Stacie Gaines",
    "city": "EWEVILLE",
    "joined": "2014-01-17T12:38:01 +05:00"
  },
  {
    "name": "Martina Russo",
    "city": "ZILLACOM",
    "joined": "2015-04-02T10:42:52 +05:00"
  },
  {
    "name": "Lynnette Fitzgerald",
    "city": "RONBERT",
    "joined": "2014-08-15T07:30:22 +05:00"
  },
  {
    "name": "Golden Pitts",
    "city": "COLLAIRE",
    "joined": "2014-06-03T01:21:33 +05:00"
  },
  {
    "name": "Carla Emerson",
    "city": "BIOTICA",
    "joined": "2014-09-01T05:11:47 +05:00"
  },
  {
    "name": "Russell Conrad",
    "city": "GLUID",
    "joined": "2014-01-11T09:34:04 +05:00"
  },
  {
    "name": "Kendra Rogers",
    "city": "ZILLANET",
    "joined": "2015-08-15T02:33:41 +05:00"
  },
  {
    "name": "Pope Eaton",
    "city": "ZOINAGE",
    "joined": "2014-09-11T08:34:37 +05:00"
  },
  {
    "name": "Alford Osborn",
    "city": "OVATION",
    "joined": "2015-06-18T05:47:13 +05:00"
  },
  {
    "name": "Lynne Watson",
    "city": "INSURESYS",
    "joined": "2014-01-10T03:35:49 +05:00"
  },
  {
    "name": "Marisol Goodman",
    "city": "INSOURCE",
    "joined": "2015-07-01T10:17:21 +05:00"
  },
  {
    "name": "Marian Rosario",
    "city": "URBANSHEE",
    "joined": "2014-03-10T08:40:49 +05:00"
  },
  {
    "name": "Patton Espinoza",
    "city": "COMVEYER",
    "joined": "2014-05-01T04:40:20 +05:00"
  },
  {
    "name": "Stacey Chambers",
    "city": "EDECINE",
    "joined": "2014-02-07T07:30:22 +05:00"
  },
  {
    "name": "Page Casey",
    "city": "SNORUS",
    "joined": "2015-07-13T04:55:55 +05:00"
  },
  {
    "name": "Ramirez Bean",
    "city": "MAXIMIND",
    "joined": "2014-09-11T03:52:23 +05:00"
  },
  {
    "name": "Barton Leonard",
    "city": "ECLIPSENT",
    "joined": "2015-02-03T06:51:52 +05:00"
  },
  {
    "name": "Gay Porter",
    "city": "BUZZWORKS",
    "joined": "2014-03-30T06:38:58 +05:00"
  },
  {
    "name": "Christian Graves",
    "city": "JETSILK",
    "joined": "2015-03-09T07:39:24 +05:00"
  },
  {
    "name": "Sabrina Kaufman",
    "city": "ZAPPIX",
    "joined": "2014-06-21T10:34:15 +05:00"
  },
  {
    "name": "Bright Jarvis",
    "city": "CAPSCREEN",
    "joined": "2014-02-21T04:12:49 +05:00"
  },
  {
    "name": "Mejia Finley",
    "city": "JUNIPOOR",
    "joined": "2014-12-28T08:25:00 +05:00"
  },
  {
    "name": "Frank Webster",
    "city": "SUPREMIA",
    "joined": "2015-07-04T09:09:40 +05:00"
  },
  {
    "name": "Hanson Mccarthy",
    "city": "MANGELICA",
    "joined": "2015-01-29T01:29:41 +05:00"
  },
  {
    "name": "Glass Petty",
    "city": "EXTRAGEN",
    "joined": "2014-12-07T05:31:11 +05:00"
  },
  {
    "name": "Noemi Burks",
    "city": "LIQUIDOC",
    "joined": "2015-03-06T04:28:02 +05:00"
  },
  {
    "name": "Millie Luna",
    "city": "ENTOGROK",
    "joined": "2015-03-02T01:07:12 +05:00"
  },
  {
    "name": "Ramona Franks",
    "city": "ACCIDENCY",
    "joined": "2015-05-18T09:44:47 +05:00"
  },
  {
    "name": "Luz Green",
    "city": "PARLEYNET",
    "joined": "2014-12-06T03:41:07 +05:00"
  },
  {
    "name": "Dana Cruz",
    "city": "DATAGENE",
    "joined": "2015-08-15T08:38:12 +05:00"
  },
  {
    "name": "Brenda Harmon",
    "city": "TETRATREX",
    "joined": "2014-10-25T04:19:38 +05:00"
  },
  {
    "name": "Rodgers Mclaughlin",
    "city": "APPLIDEC",
    "joined": "2015-08-12T09:47:23 +05:00"
  },
  {
    "name": "Cooper Simmons",
    "city": "AMRIL",
    "joined": "2014-04-03T12:26:09 +05:00"
  },
  {
    "name": "Reyes Vang",
    "city": "BYTREX",
    "joined": "2014-10-12T05:58:51 +05:00"
  },
  {
    "name": "Maribel Hobbs",
    "city": "DEEPENDS",
    "joined": "2014-09-03T04:29:04 +05:00"
  },
  {
    "name": "Jensen Douglas",
    "city": "ZIPAK",
    "joined": "2015-06-20T08:06:12 +05:00"
  },
  {
    "name": "Letha Walter",
    "city": "VIRXO",
    "joined": "2014-08-31T08:50:23 +05:00"
  },
  {
    "name": "Sims Knox",
    "city": "EARGO",
    "joined": "2014-01-08T03:28:24 +05:00"
  },
  {
    "name": "Kelley Alvarado",
    "city": "FUTURIZE",
    "joined": "2014-04-10T05:03:05 +05:00"
  },
  {
    "name": "Teri Holland",
    "city": "AUSTEX",
    "joined": "2014-02-19T05:08:47 +05:00"
  },
  {
    "name": "Nellie Shannon",
    "city": "ZOID",
    "joined": "2014-08-30T08:28:48 +05:00"
  },
  {
    "name": "Trujillo Hendricks",
    "city": "SCHOOLIO",
    "joined": "2015-07-09T11:49:51 +05:00"
  },
  {
    "name": "Mendoza Monroe",
    "city": "SYNKGEN",
    "joined": "2015-04-06T11:08:25 +05:00"
  },
  {
    "name": "Wallace Rivera",
    "city": "QUONK",
    "joined": "2014-09-13T11:12:03 +05:00"
  },
  {
    "name": "Earline Conner",
    "city": "EARWAX",
    "joined": "2014-04-12T10:19:24 +05:00"
  },
  {
    "name": "Waters Fry",
    "city": "IZZBY",
    "joined": "2015-06-10T02:58:08 +05:00"
  },
  {
    "name": "Matilda Lawrence",
    "city": "GEEKNET",
    "joined": "2015-07-09T03:01:42 +05:00"
  },
  {
    "name": "Hancock Tyler",
    "city": "KAGE",
    "joined": "2015-07-02T03:38:33 +05:00"
  },
  {
    "name": "Claudia Moody",
    "city": "ECSTASIA",
    "joined": "2015-07-28T02:56:51 +05:00"
  },
  {
    "name": "Moreno Sargent",
    "city": "DOGSPA",
    "joined": "2014-12-16T02:55:46 +05:00"
  },
  {
    "name": "Robin Mckay",
    "city": "XIXAN",
    "joined": "2014-10-03T05:12:21 +05:00"
  },
  {
    "name": "Carole Bird",
    "city": "SEQUITUR",
    "joined": "2015-01-05T11:08:27 +05:00"
  },
  {
    "name": "Mccoy Blair",
    "city": "GEEKOL",
    "joined": "2014-08-30T04:58:45 +05:00"
  },
  {
    "name": "Cathryn Whitney",
    "city": "ZIZZLE",
    "joined": "2014-08-12T02:26:16 +05:00"
  },
  {
    "name": "Tyson House",
    "city": "UPLINX",
    "joined": "2014-07-19T06:57:11 +05:00"
  },
  {
    "name": "Spence Juarez",
    "city": "VIOCULAR",
    "joined": "2014-07-23T05:46:17 +05:00"
  },
  {
    "name": "Kaye Foreman",
    "city": "UTARA",
    "joined": "2015-08-26T02:24:33 +05:00"
  },
  {
    "name": "Silva Sweet",
    "city": "BOILCAT",
    "joined": "2015-04-18T01:37:09 +05:00"
  },
  {
    "name": "Diaz Crawford",
    "city": "PRIMORDIA",
    "joined": "2014-09-21T09:18:29 +05:00"
  },
  {
    "name": "Horne Nichols",
    "city": "NAVIR",
    "joined": "2014-10-31T02:52:54 +05:00"
  },
  {
    "name": "Ryan Lowery",
    "city": "BLURRYBUS",
    "joined": "2015-05-01T08:56:05 +05:00"
  },
  {
    "name": "Karina Joyce",
    "city": "GEEKY",
    "joined": "2015-07-26T12:31:14 +05:00"
  },
  {
    "name": "Santiago Manning",
    "city": "OPTICON",
    "joined": "2014-01-10T12:01:07 +05:00"
  },
  {
    "name": "Hillary Slater",
    "city": "PHARMEX",
    "joined": "2015-07-03T06:33:01 +05:00"
  },
  {
    "name": "Robbins Walker",
    "city": "PERMADYNE",
    "joined": "2015-02-23T08:10:48 +05:00"
  },
  {
    "name": "Casey Guzman",
    "city": "COGENTRY",
    "joined": "2015-06-22T03:25:51 +05:00"
  },
  {
    "name": "Leanna Lane",
    "city": "GENEKOM",
    "joined": "2014-01-31T12:43:17 +05:00"
  },
  {
    "name": "Winnie Shepherd",
    "city": "ZENSOR",
    "joined": "2015-06-30T03:46:08 +05:00"
  },
  {
    "name": "Alyce Wilson",
    "city": "ISOSPHERE",
    "joined": "2014-10-12T06:19:21 +05:00"
  },
  {
    "name": "Suarez Walls",
    "city": "GEEKWAGON",
    "joined": "2014-11-11T10:42:40 +05:00"
  },
  {
    "name": "Savage Lamb",
    "city": "NIMON",
    "joined": "2015-07-19T05:22:57 +05:00"
  },
  {
    "name": "Riley Hall",
    "city": "SCENTRIC",
    "joined": "2014-12-19T11:27:36 +05:00"
  },
  {
    "name": "Richards Hanson",
    "city": "VIDTO",
    "joined": "2014-07-20T11:00:59 +05:00"
  },
  {
    "name": "Juliet Goodwin",
    "city": "SURETECH",
    "joined": "2014-03-29T10:53:50 +05:00"
  },
  {
    "name": "Austin Hardy",
    "city": "TALKALOT",
    "joined": "2014-10-02T11:15:07 +05:00"
  },
  {
    "name": "Susana Miller",
    "city": "WRAPTURE",
    "joined": "2014-03-10T10:00:54 +05:00"
  },
  {
    "name": "Acevedo Mccall",
    "city": "ZENTRY",
    "joined": "2015-08-31T04:55:35 +05:00"
  },
  {
    "name": "Robinson Gross",
    "city": "MANGLO",
    "joined": "2014-01-30T08:16:39 +05:00"
  },
  {
    "name": "Vincent Simpson",
    "city": "ASIMILINE",
    "joined": "2015-07-16T12:19:02 +05:00"
  },
  {
    "name": "Hendricks Campos",
    "city": "BEDDER",
    "joined": "2014-04-14T05:42:43 +05:00"
  },
  {
    "name": "Blackwell Hester",
    "city": "ZAJ",
    "joined": "2015-02-19T05:25:39 +05:00"
  },
  {
    "name": "Shelton Bowers",
    "city": "KRAG",
    "joined": "2014-05-23T02:54:42 +05:00"
  },
  {
    "name": "Moody Carrillo",
    "city": "GALLAXIA",
    "joined": "2014-04-14T03:33:51 +05:00"
  },
  {
    "name": "Gibbs Willis",
    "city": "CEDWARD",
    "joined": "2014-04-30T01:47:35 +05:00"
  },
  {
    "name": "Hubbard Newman",
    "city": "BULLJUICE",
    "joined": "2014-04-23T04:20:31 +05:00"
  },
  {
    "name": "Miller Molina",
    "city": "ZENTIA",
    "joined": "2014-09-16T11:27:08 +05:00"
  },
  {
    "name": "Priscilla Parsons",
    "city": "COSMOSIS",
    "joined": "2014-06-01T10:22:11 +05:00"
  },
  {
    "name": "Ingram Head",
    "city": "ENQUILITY",
    "joined": "2014-12-30T04:35:00 +05:00"
  },
  {
    "name": "Etta Morse",
    "city": "BOILICON",
    "joined": "2014-10-08T01:05:13 +05:00"
  },
  {
    "name": "Phelps Evans",
    "city": "GOGOL",
    "joined": "2014-02-09T04:58:34 +05:00"
  },
  {
    "name": "Johnston Payne",
    "city": "EARTHPLEX",
    "joined": "2015-07-10T01:33:16 +05:00"
  },
  {
    "name": "Haney Houston",
    "city": "SHADEASE",
    "joined": "2014-05-13T12:06:12 +05:00"
  },
  {
    "name": "Sheryl Guerrero",
    "city": "ZOMBOID",
    "joined": "2015-03-14T07:45:01 +05:00"
  },
  {
    "name": "Heather England",
    "city": "HINWAY",
    "joined": "2014-07-30T04:26:54 +05:00"
  },
  {
    "name": "Crawford Dunlap",
    "city": "TWIIST",
    "joined": "2015-08-15T05:46:49 +05:00"
  },
  {
    "name": "Irwin Craig",
    "city": "FITCORE",
    "joined": "2014-12-06T02:11:20 +05:00"
  },
  {
    "name": "Jordan Wyatt",
    "city": "ISBOL",
    "joined": "2014-08-30T05:37:12 +05:00"
  },
  {
    "name": "Karen Welch",
    "city": "TECHTRIX",
    "joined": "2014-09-07T04:10:00 +05:00"
  },
  {
    "name": "Farrell Rodriguez",
    "city": "ENTROPIX",
    "joined": "2015-07-19T04:11:54 +05:00"
  },
  {
    "name": "Solis Ballard",
    "city": "MAGNINA",
    "joined": "2014-06-07T02:44:38 +05:00"
  },
  {
    "name": "Kristy Burton",
    "city": "ELEMANTRA",
    "joined": "2014-03-08T07:05:47 +05:00"
  },
  {
    "name": "Kim Saunders",
    "city": "XYMONK",
    "joined": "2015-08-31T04:23:07 +05:00"
  },
  {
    "name": "James Langley",
    "city": "GENMOM",
    "joined": "2014-03-30T05:40:26 +05:00"
  },
  {
    "name": "Gould Figueroa",
    "city": "RECRISYS",
    "joined": "2014-12-03T03:33:12 +05:00"
  },
  {
    "name": "Ollie Munoz",
    "city": "KINDALOO",
    "joined": "2014-09-30T01:07:12 +05:00"
  },
  {
    "name": "Tammi Mitchell",
    "city": "RODEOCEAN",
    "joined": "2015-08-05T11:57:39 +05:00"
  },
  {
    "name": "Chambers Gilliam",
    "city": "VIXO",
    "joined": "2014-06-07T03:58:55 +05:00"
  },
  {
    "name": "Daniel Sanford",
    "city": "ZBOO",
    "joined": "2014-02-05T06:37:39 +05:00"
  },
  {
    "name": "Elise Blackburn",
    "city": "PASTURIA",
    "joined": "2015-07-08T05:44:19 +05:00"
  },
  {
    "name": "Hansen Mann",
    "city": "TERASCAPE",
    "joined": "2014-12-19T09:41:33 +05:00"
  },
  {
    "name": "Stanton Lancaster",
    "city": "MAXEMIA",
    "joined": "2014-05-13T07:12:49 +05:00"
  },
  {
    "name": "Ramos Bullock",
    "city": "PANZENT",
    "joined": "2015-07-30T09:34:41 +05:00"
  },
  {
    "name": "Briana Meyer",
    "city": "INTERGEEK",
    "joined": "2015-08-08T01:35:47 +05:00"
  },
  {
    "name": "Lorna Rich",
    "city": "BOINK",
    "joined": "2015-06-26T12:37:58 +05:00"
  },
  {
    "name": "Heidi Dorsey",
    "city": "TALKOLA",
    "joined": "2014-05-29T07:02:39 +05:00"
  },
  {
    "name": "Stephenson Cervantes",
    "city": "NAXDIS",
    "joined": "2014-02-08T07:56:42 +05:00"
  },
  {
    "name": "Kelly Sosa",
    "city": "BISBA",
    "joined": "2015-06-06T11:19:31 +05:00"
  },
  {
    "name": "Camille Myers",
    "city": "INTERLOO",
    "joined": "2014-02-24T10:57:48 +05:00"
  },
  {
    "name": "Sears Park",
    "city": "ZENTILITY",
    "joined": "2014-05-11T02:47:21 +05:00"
  },
  {
    "name": "Jeanine Keith",
    "city": "IMAGINART",
    "joined": "2015-08-26T12:02:43 +05:00"
  },
  {
    "name": "Rosemarie Murray",
    "city": "ACRODANCE",
    "joined": "2015-08-11T03:05:12 +05:00"
  },
  {
    "name": "Rios Hill",
    "city": "CYCLONICA",
    "joined": "2015-09-01T09:27:38 +05:00"
  },
  {
    "name": "Dawn Delgado",
    "city": "XERONK",
    "joined": "2015-03-30T07:34:32 +05:00"
  },
  {
    "name": "Pam Anderson",
    "city": "GADTRON",
    "joined": "2015-03-21T07:01:49 +05:00"
  },
  {
    "name": "Victoria Wagner",
    "city": "WEBIOTIC",
    "joined": "2015-01-13T11:10:43 +05:00"
  },
  {
    "name": "Imogene Armstrong",
    "city": "AUSTECH",
    "joined": "2014-03-09T11:38:29 +05:00"
  },
  {
    "name": "Ortiz Duffy",
    "city": "ACIUM",
    "joined": "2015-08-25T06:24:25 +05:00"
  },
  {
    "name": "Beverly Brennan",
    "city": "JASPER",
    "joined": "2015-01-04T10:08:58 +05:00"
  },
  {
    "name": "Wilda Rollins",
    "city": "MULTIFLEX",
    "joined": "2014-07-28T11:32:11 +05:00"
  },
  {
    "name": "Nikki Best",
    "city": "CUJO",
    "joined": "2014-09-07T07:34:12 +05:00"
  },
  {
    "name": "Peters Colon",
    "city": "KONGENE",
    "joined": "2015-06-28T04:57:52 +05:00"
  },
  {
    "name": "Sloan Spencer",
    "city": "FLUM",
    "joined": "2014-08-03T10:35:48 +05:00"
  },
  {
    "name": "Brewer Ray",
    "city": "EPLODE",
    "joined": "2015-04-21T12:59:39 +05:00"
  },
  {
    "name": "Watson Howe",
    "city": "BICOL",
    "joined": "2014-03-16T11:47:18 +05:00"
  },
  {
    "name": "Irene Hoover",
    "city": "ZYTREK",
    "joined": "2014-11-10T03:48:45 +05:00"
  },
  {
    "name": "Webb Key",
    "city": "NEUROCELL",
    "joined": "2014-09-29T03:19:26 +05:00"
  },
  {
    "name": "Snider Ramos",
    "city": "ENERSOL",
    "joined": "2015-01-27T06:02:09 +05:00"
  },
  {
    "name": "Alba Campbell",
    "city": "TECHADE",
    "joined": "2014-10-05T09:39:48 +05:00"
  },
  {
    "name": "Sweet Davis",
    "city": "GEEKFARM",
    "joined": "2014-10-20T02:43:27 +05:00"
  },
  {
    "name": "Beulah Alexander",
    "city": "ENJOLA",
    "joined": "2015-07-15T04:49:22 +05:00"
  },
  {
    "name": "Penny Boyer",
    "city": "BITTOR",
    "joined": "2015-03-25T09:09:37 +05:00"
  },
  {
    "name": "Holland Rodriquez",
    "city": "SNACKTION",
    "joined": "2014-09-27T09:51:35 +05:00"
  },
  {
    "name": "Keller Ortiz",
    "city": "INTERFIND",
    "joined": "2014-01-30T07:11:26 +05:00"
  },
  {
    "name": "Powers Hyde",
    "city": "OATFARM",
    "joined": "2015-06-11T08:02:52 +05:00"
  },
  {
    "name": "Estes Coffey",
    "city": "ZYPLE",
    "joined": "2014-10-21T09:40:08 +05:00"
  },
  {
    "name": "Young Gonzalez",
    "city": "FILODYNE",
    "joined": "2015-09-02T05:19:30 +05:00"
  },
  {
    "name": "Sykes Strickland",
    "city": "KLUGGER",
    "joined": "2015-05-13T04:41:24 +05:00"
  },
  {
    "name": "Collins Scott",
    "city": "MIRACLIS",
    "joined": "2014-08-03T06:35:15 +05:00"
  },
  {
    "name": "Castillo Newton",
    "city": "FRANSCENE",
    "joined": "2014-08-19T08:18:50 +05:00"
  },
  {
    "name": "Yvonne Delacruz",
    "city": "BUGSALL",
    "joined": "2014-04-24T11:10:43 +05:00"
  },
  {
    "name": "Richard Gates",
    "city": "GINKLE",
    "joined": "2014-06-10T12:46:54 +05:00"
  },
  {
    "name": "Stevens Randall",
    "city": "TUBALUM",
    "joined": "2015-01-15T03:14:03 +05:00"
  },
  {
    "name": "Katina Hodge",
    "city": "SONGBIRD",
    "joined": "2014-02-25T12:05:43 +05:00"
  },
  {
    "name": "Burton Velez",
    "city": "LIMAGE",
    "joined": "2014-04-13T04:24:18 +05:00"
  },
  {
    "name": "Maria Dillard",
    "city": "ECLIPTO",
    "joined": "2015-08-07T03:29:13 +05:00"
  },
  {
    "name": "Flossie Cantu",
    "city": "ZOGAK",
    "joined": "2015-04-22T07:35:59 +05:00"
  },
  {
    "name": "Tabitha Copeland",
    "city": "NETROPIC",
    "joined": "2014-01-12T06:19:47 +05:00"
  },
  {
    "name": "Naomi Sheppard",
    "city": "ELITA",
    "joined": "2014-07-17T04:54:33 +05:00"
  },
  {
    "name": "Cummings Mosley",
    "city": "XURBAN",
    "joined": "2015-02-21T11:37:05 +05:00"
  },
  {
    "name": "Stafford White",
    "city": "SOPRANO",
    "joined": "2014-12-05T10:08:22 +05:00"
  },
  {
    "name": "Jerri Orr",
    "city": "SPRINGBEE",
    "joined": "2014-06-27T11:21:31 +05:00"
  },
  {
    "name": "Katharine Landry",
    "city": "AUTOMON",
    "joined": "2014-05-23T09:20:54 +05:00"
  },
  {
    "name": "Lucia Davidson",
    "city": "BOLAX",
    "joined": "2015-08-13T09:16:14 +05:00"
  },
  {
    "name": "Logan Craft",
    "city": "UBERLUX",
    "joined": "2014-11-18T02:34:25 +05:00"
  },
  {
    "name": "Schneider Franco",
    "city": "QNEKT",
    "joined": "2015-03-18T05:56:59 +05:00"
  },
  {
    "name": "Mabel Shaffer",
    "city": "ARCHITAX",
    "joined": "2015-03-31T07:26:10 +05:00"
  },
  {
    "name": "Juanita Hampton",
    "city": "FURNAFIX",
    "joined": "2015-07-23T07:45:01 +05:00"
  },
  {
    "name": "Payne Ashley",
    "city": "KAGGLE",
    "joined": "2014-04-28T01:13:52 +05:00"
  },
  {
    "name": "Maureen Lewis",
    "city": "MOBILDATA",
    "joined": "2014-06-15T10:57:46 +05:00"
  },
  {
    "name": "Bruce Jones",
    "city": "VIASIA",
    "joined": "2014-08-01T09:12:56 +05:00"
  },
  {
    "name": "Larsen Farley",
    "city": "CALCULA",
    "joined": "2015-03-13T10:43:50 +05:00"
  },
  {
    "name": "Bobbie Hensley",
    "city": "PORTICO",
    "joined": "2014-03-17T02:56:58 +05:00"
  },
  {
    "name": "Vaughn Schwartz",
    "city": "TETAK",
    "joined": "2014-07-25T01:11:33 +05:00"
  },
  {
    "name": "Erma Holder",
    "city": "BUZZNESS",
    "joined": "2015-04-09T05:51:57 +05:00"
  },
  {
    "name": "Blake Chaney",
    "city": "ISOSTREAM",
    "joined": "2014-02-18T10:35:55 +05:00"
  },
  {
    "name": "Watts Mueller",
    "city": "UNIWORLD",
    "joined": "2015-03-08T12:41:25 +05:00"
  },
  {
    "name": "Fleming Schroeder",
    "city": "EARTHMARK",
    "joined": "2015-03-12T06:12:21 +05:00"
  },
  {
    "name": "Sheri Ortega",
    "city": "DENTREX",
    "joined": "2014-06-07T02:27:59 +05:00"
  },
  {
    "name": "Schwartz Weaver",
    "city": "GLUKGLUK",
    "joined": "2015-08-08T01:54:07 +05:00"
  },
  {
    "name": "Lynn Valencia",
    "city": "POWERNET",
    "joined": "2015-08-13T09:36:44 +05:00"
  },
  {
    "name": "Jeannine York",
    "city": "ZYTRAC",
    "joined": "2014-09-26T08:30:15 +05:00"
  },
  {
    "name": "Weber Garcia",
    "city": "KIOSK",
    "joined": "2014-11-22T10:46:37 +05:00"
  },
  {
    "name": "Lindsay Wallace",
    "city": "APPLIDECK",
    "joined": "2014-04-25T02:13:21 +05:00"
  },
  {
    "name": "Haley Acevedo",
    "city": "COMTOURS",
    "joined": "2015-03-24T12:56:07 +05:00"
  },
  {
    "name": "Colette Foster",
    "city": "MARQET",
    "joined": "2014-12-13T06:07:11 +05:00"
  },
  {
    "name": "Avila Nielsen",
    "city": "JAMNATION",
    "joined": "2014-05-19T06:56:29 +05:00"
  },
  {
    "name": "Tessa Daugherty",
    "city": "CENTREXIN",
    "joined": "2015-08-24T11:23:14 +05:00"
  },
  {
    "name": "Duran Dixon",
    "city": "GEEKKO",
    "joined": "2014-01-24T04:31:15 +05:00"
  },
  {
    "name": "Katrina Hansen",
    "city": "ENDIPIN",
    "joined": "2014-02-05T02:59:30 +05:00"
  },
  {
    "name": "Fuller Hubbard",
    "city": "ORBIN",
    "joined": "2014-04-06T09:58:16 +05:00"
  },
  {
    "name": "Barker Gill",
    "city": "SLOGANAUT",
    "joined": "2015-01-22T02:56:58 +05:00"
  },
  {
    "name": "Odom Jenkins",
    "city": "GLOBOIL",
    "joined": "2014-08-02T09:00:16 +05:00"
  },
  {
    "name": "Edith Justice",
    "city": "COMSTRUCT",
    "joined": "2015-03-18T12:39:22 +05:00"
  },
  {
    "name": "Forbes Bradford",
    "city": "TERRAGO",
    "joined": "2015-03-01T04:48:21 +05:00"
  },
  {
    "name": "Inez Sharpe",
    "city": "MOREGANIC",
    "joined": "2015-07-09T03:14:15 +05:00"
  },
  {
    "name": "Anne Clark",
    "city": "HYPLEX",
    "joined": "2015-06-03T03:26:52 +05:00"
  },
  {
    "name": "Shaw Mills",
    "city": "STRALOY",
    "joined": "2014-03-16T12:27:31 +05:00"
  },
  {
    "name": "Alberta Becker",
    "city": "ORONOKO",
    "joined": "2014-04-28T09:59:44 +05:00"
  },
  {
    "name": "Harris Caldwell",
    "city": "GEEKOLA",
    "joined": "2015-07-02T06:20:10 +05:00"
  },
  {
    "name": "Enid Stokes",
    "city": "LYRICHORD",
    "joined": "2014-07-10T12:08:22 +05:00"
  },
  {
    "name": "Wade Nelson",
    "city": "COMVENE",
    "joined": "2014-10-24T07:22:08 +05:00"
  },
  {
    "name": "Roslyn Reilly",
    "city": "EXPOSA",
    "joined": "2015-08-21T06:55:00 +05:00"
  },
  {
    "name": "Gilbert Good",
    "city": "IDEGO",
    "joined": "2015-08-28T12:19:17 +05:00"
  },
  {
    "name": "Lester Arnold",
    "city": "MUSAPHICS",
    "joined": "2015-03-10T09:30:33 +05:00"
  },
  {
    "name": "Dean Robles",
    "city": "ENORMO",
    "joined": "2014-03-09T01:56:20 +05:00"
  },
  {
    "name": "Eve Collier",
    "city": "GEOFARM",
    "joined": "2014-08-12T12:46:23 +05:00"
  },
  {
    "name": "Morin Peterson",
    "city": "SUREPLEX",
    "joined": "2015-07-15T05:19:04 +05:00"
  },
  {
    "name": "Cathleen Harper",
    "city": "ECOSYS",
    "joined": "2014-06-04T12:17:50 +05:00"
  },
  {
    "name": "Kimberley Bradley",
    "city": "SPLINX",
    "joined": "2015-03-21T03:42:34 +05:00"
  },
  {
    "name": "Leonor Rodgers",
    "city": "ZOLAVO",
    "joined": "2014-12-08T11:01:46 +05:00"
  },
  {
    "name": "Lily Edwards",
    "city": "ZORK",
    "joined": "2014-01-03T10:58:02 +05:00"
  },
  {
    "name": "Mcbride Oliver",
    "city": "ZANITY",
    "joined": "2014-06-23T12:38:54 +05:00"
  },
  {
    "name": "Glenn Stewart",
    "city": "COMTOUR",
    "joined": "2015-04-01T05:55:51 +05:00"
  },
  {
    "name": "Rosemary Bauer",
    "city": "REMOTION",
    "joined": "2015-03-20T04:00:07 +05:00"
  },
  {
    "name": "Bean Cummings",
    "city": "ICOLOGY",
    "joined": "2015-07-29T02:03:57 +05:00"
  },
  {
    "name": "Willa Tyson",
    "city": "STREZZO",
    "joined": "2015-01-12T07:59:45 +05:00"
  },
  {
    "name": "Lillie Reese",
    "city": "ISOPOP",
    "joined": "2014-04-30T04:29:57 +05:00"
  },
  {
    "name": "Mollie Bernard",
    "city": "COMFIRM",
    "joined": "2014-08-02T12:25:48 +05:00"
  },
  {
    "name": "Shelia Morrison",
    "city": "CALCU",
    "joined": "2015-01-29T10:56:23 +05:00"
  },
  {
    "name": "Natalia Hunt",
    "city": "TSUNAMIA",
    "joined": "2014-03-18T03:35:23 +05:00"
  },
  {
    "name": "Bernadette Robinson",
    "city": "DADABASE",
    "joined": "2014-07-22T05:39:19 +05:00"
  },
  {
    "name": "Yates Clayton",
    "city": "ZIALACTIC",
    "joined": "2015-03-13T12:09:58 +05:00"
  },
  {
    "name": "Shanna Booker",
    "city": "ROUGHIES",
    "joined": "2015-02-05T02:06:31 +05:00"
  },
  {
    "name": "Holcomb Ruiz",
    "city": "SENSATE",
    "joined": "2014-01-15T03:05:32 +05:00"
  },
  {
    "name": "Lila Warren",
    "city": "OPTYK",
    "joined": "2015-04-08T08:07:54 +05:00"
  },
  {
    "name": "Oneal Cash",
    "city": "SUREMAX",
    "joined": "2014-04-15T07:43:20 +05:00"
  },
  {
    "name": "Alexander Hancock",
    "city": "FLYBOYZ",
    "joined": "2015-04-20T02:27:27 +05:00"
  },
  {
    "name": "Cline Haynes",
    "city": "PAPRIKUT",
    "joined": "2014-11-18T06:24:12 +05:00"
  },
  {
    "name": "Eunice Spence",
    "city": "ACRUEX",
    "joined": "2014-06-05T03:26:36 +05:00"
  },
  {
    "name": "Pace Raymond",
    "city": "NETUR",
    "joined": "2014-12-13T12:56:48 +05:00"
  },
  {
    "name": "Davidson Sweeney",
    "city": "IMKAN",
    "joined": "2015-04-26T12:57:38 +05:00"
  },
  {
    "name": "Frost Roberson",
    "city": "APEXIA",
    "joined": "2015-06-25T06:57:36 +05:00"
  },
  {
    "name": "Collier Bennett",
    "city": "MEDALERT",
    "joined": "2014-08-10T06:55:34 +05:00"
  },
  {
    "name": "Monica Jordan",
    "city": "ENERVATE",
    "joined": "2015-02-23T06:28:23 +05:00"
  },
  {
    "name": "Angelia Moon",
    "city": "MEGALL",
    "joined": "2014-12-05T06:02:14 +05:00"
  },
  {
    "name": "Best Grant",
    "city": "IPLAX",
    "joined": "2015-06-16T01:28:38 +05:00"
  },
  {
    "name": "Pittman Durham",
    "city": "DOGTOWN",
    "joined": "2015-05-14T03:29:22 +05:00"
  },
  {
    "name": "Freda Fletcher",
    "city": "CYTREX",
    "joined": "2014-03-29T11:04:14 +05:00"
  },
  {
    "name": "Chen Bryant",
    "city": "TRANSLINK",
    "joined": "2015-06-05T11:17:12 +05:00"
  },
  {
    "name": "Crane Joyner",
    "city": "BESTO",
    "joined": "2015-02-28T06:52:40 +05:00"
  },
  {
    "name": "Mallory Whitfield",
    "city": "ZORROMOP",
    "joined": "2014-11-18T04:47:02 +05:00"
  },
  {
    "name": "Lawanda Huffman",
    "city": "OBLIQ",
    "joined": "2014-08-08T11:33:46 +05:00"
  },
  {
    "name": "Stuart Rocha",
    "city": "ZENTURY",
    "joined": "2014-11-29T12:41:10 +05:00"
  },
  {
    "name": "Bentley Rosa",
    "city": "ARTIQ",
    "joined": "2015-06-06T08:16:20 +05:00"
  },
  {
    "name": "Sherri Hines",
    "city": "DIGITALUS",
    "joined": "2014-10-18T07:06:03 +05:00"
  },
  {
    "name": "Bettie Quinn",
    "city": "ACCUPHARM",
    "joined": "2015-05-27T08:31:00 +05:00"
  },
  {
    "name": "Compton Mendoza",
    "city": "MEMORA",
    "joined": "2015-02-16T08:19:21 +05:00"
  },
  {
    "name": "Spears Martin",
    "city": "EVIDENDS",
    "joined": "2014-01-21T03:50:34 +05:00"
  },
  {
    "name": "Carol Le",
    "city": "PLASMOX",
    "joined": "2014-08-04T08:14:10 +05:00"
  },
  {
    "name": "Alissa Mooney",
    "city": "EXOVENT",
    "joined": "2014-03-27T05:03:42 +05:00"
  },
  {
    "name": "Ella Mathis",
    "city": "LOVEPAD",
    "joined": "2014-06-12T05:16:59 +05:00"
  },
  {
    "name": "Shannon Deleon",
    "city": "QUIZMO",
    "joined": "2014-12-29T06:01:53 +05:00"
  },
  {
    "name": "Horton Burt",
    "city": "COMTRAIL",
    "joined": "2015-08-21T12:02:02 +05:00"
  },
  {
    "name": "Tracie Waters",
    "city": "ZILLACTIC",
    "joined": "2015-06-10T03:56:18 +05:00"
  },
  {
    "name": "Price Koch",
    "city": "REALYSIS",
    "joined": "2014-04-09T10:05:42 +05:00"
  },
  {
    "name": "Frances Morrow",
    "city": "GORGANIC",
    "joined": "2014-10-31T03:37:14 +05:00"
  },
  {
    "name": "Delores Vaughan",
    "city": "CONCILITY",
    "joined": "2015-05-06T11:58:03 +05:00"
  },
  {
    "name": "Singleton Benjamin",
    "city": "CRUSTATIA",
    "joined": "2015-02-12T01:41:13 +05:00"
  },
  {
    "name": "Muriel Sherman",
    "city": "VELOS",
    "joined": "2015-05-04T10:20:24 +05:00"
  },
  {
    "name": "Bryan Russell",
    "city": "VALPREAL",
    "joined": "2014-08-22T02:54:30 +05:00"
  },
  {
    "name": "Sosa Barnes",
    "city": "INSURON",
    "joined": "2014-07-21T07:40:06 +05:00"
  },
  {
    "name": "Melanie Buckner",
    "city": "SYNTAC",
    "joined": "2014-12-19T05:38:20 +05:00"
  },
  {
    "name": "Chasity Cox",
    "city": "LOCAZONE",
    "joined": "2014-05-13T04:38:50 +05:00"
  },
  {
    "name": "Montgomery Hutchinson",
    "city": "POLARAX",
    "joined": "2014-06-22T01:27:27 +05:00"
  },
  {
    "name": "Gena Frye",
    "city": "FROLIX",
    "joined": "2014-12-12T05:31:12 +05:00"
  },
  {
    "name": "Gentry Garrett",
    "city": "OMATOM",
    "joined": "2015-01-10T05:03:42 +05:00"
  },
  {
    "name": "Lesa Mercer",
    "city": "REMOLD",
    "joined": "2014-01-28T07:44:34 +05:00"
  },
  {
    "name": "Susie Kinney",
    "city": "EWAVES",
    "joined": "2014-12-09T03:52:05 +05:00"
  },
  {
    "name": "Betty Combs",
    "city": "KOOGLE",
    "joined": "2014-04-26T04:43:25 +05:00"
  },
  {
    "name": "Catherine Hawkins",
    "city": "KENGEN",
    "joined": "2014-04-07T08:52:03 +05:00"
  },
  {
    "name": "Estela Pratt",
    "city": "XIIX",
    "joined": "2014-12-24T11:05:47 +05:00"
  },
  {
    "name": "Lawrence Sims",
    "city": "NIQUENT",
    "joined": "2015-02-17T01:46:23 +05:00"
  },
  {
    "name": "Lora Roach",
    "city": "GEEKULAR",
    "joined": "2014-08-17T05:45:23 +05:00"
  },
  {
    "name": "Mays Grimes",
    "city": "AEORA",
    "joined": "2015-03-28T05:58:03 +05:00"
  },
  {
    "name": "Evangelina Taylor",
    "city": "STUCCO",
    "joined": "2014-05-23T08:24:01 +05:00"
  },
  {
    "name": "Joyce Stark",
    "city": "VERAQ",
    "joined": "2014-04-13T02:21:08 +05:00"
  },
  {
    "name": "Witt Townsend",
    "city": "EQUICOM",
    "joined": "2015-08-29T05:16:44 +05:00"
  },
  {
    "name": "Ashley Powers",
    "city": "QUOTEZART",
    "joined": "2014-10-08T08:35:44 +05:00"
  },
  {
    "name": "Celeste Rutledge",
    "city": "RAMEON",
    "joined": "2015-08-04T05:05:27 +05:00"
  },
  {
    "name": "Allie Ochoa",
    "city": "DELPHIDE",
    "joined": "2015-08-20T03:56:28 +05:00"
  },
  {
    "name": "Dale Abbott",
    "city": "OTHERSIDE",
    "joined": "2015-03-11T01:30:46 +05:00"
  },
  {
    "name": "Beck Sawyer",
    "city": "QIMONK",
    "joined": "2014-02-09T01:39:06 +05:00"
  },
  {
    "name": "Rose Briggs",
    "city": "ASSISTIA",
    "joined": "2015-04-27T01:21:05 +05:00"
  },
  {
    "name": "Melton Merrill",
    "city": "MALATHION",
    "joined": "2014-01-29T09:00:35 +05:00"
  },
  {
    "name": "Elisa Frost",
    "city": "KOFFEE",
    "joined": "2014-07-12T08:10:53 +05:00"
  },
  {
    "name": "Raymond Golden",
    "city": "PEARLESSA",
    "joined": "2014-01-28T02:49:20 +05:00"
  },
  {
    "name": "Kaitlin Neal",
    "city": "FLEETMIX",
    "joined": "2014-12-01T04:57:47 +05:00"
  },
  {
    "name": "Hall Meyers",
    "city": "QUANTASIS",
    "joined": "2015-06-01T03:33:09 +05:00"
  },
  {
    "name": "Richardson Cortez",
    "city": "ATGEN",
    "joined": "2015-07-18T08:38:00 +05:00"
  },
  {
    "name": "Faith Henry",
    "city": "JUMPSTACK",
    "joined": "2015-01-30T11:35:11 +05:00"
  },
  {
    "name": "Donaldson Graham",
    "city": "ASSURITY",
    "joined": "2014-02-01T04:56:51 +05:00"
  },
  {
    "name": "Jolene Michael",
    "city": "ISOTERNIA",
    "joined": "2015-09-02T06:26:08 +05:00"
  },
  {
    "name": "Odonnell Dejesus",
    "city": "KEENGEN",
    "joined": "2014-10-25T03:09:06 +05:00"
  },
  {
    "name": "Louella Elliott",
    "city": "THREDZ",
    "joined": "2014-06-28T07:13:47 +05:00"
  },
  {
    "name": "Vargas Bonner",
    "city": "NETPLAX",
    "joined": "2014-11-03T05:21:32 +05:00"
  },
  {
    "name": "Jennifer Carr",
    "city": "OPTIQUE",
    "joined": "2014-06-02T11:55:29 +05:00"
  },
  {
    "name": "Natalie Soto",
    "city": "DYMI",
    "joined": "2014-07-28T07:46:36 +05:00"
  },
  {
    "name": "Simpson Chen",
    "city": "PIVITOL",
    "joined": "2014-10-16T06:26:03 +05:00"
  },
  {
    "name": "Candace Hopkins",
    "city": "ISONUS",
    "joined": "2015-07-23T07:20:37 +05:00"
  },
  {
    "name": "Sandy Mcmillan",
    "city": "ZERBINA",
    "joined": "2014-09-17T02:31:53 +05:00"
  },
  {
    "name": "Lewis Livingston",
    "city": "ZYTREX",
    "joined": "2015-05-07T04:58:28 +05:00"
  },
  {
    "name": "Whitley Chan",
    "city": "XYLAR",
    "joined": "2014-09-28T05:17:52 +05:00"
  },
  {
    "name": "Julianne Guy",
    "city": "ZILENCIO",
    "joined": "2014-11-11T05:04:24 +05:00"
  },
  {
    "name": "Mason Medina",
    "city": "BOSTONIC",
    "joined": "2014-09-27T04:59:38 +05:00"
  },
  {
    "name": "Francesca May",
    "city": "SIGNIDYNE",
    "joined": "2014-09-15T07:54:50 +05:00"
  },
  {
    "name": "Esther Tran",
    "city": "OMNIGOG",
    "joined": "2014-04-01T08:15:57 +05:00"
  },
  {
    "name": "Paul Whitley",
    "city": "BRISTO",
    "joined": "2014-02-28T12:36:54 +05:00"
  },
  {
    "name": "Krista Tate",
    "city": "OCTOCORE",
    "joined": "2014-03-17T10:15:37 +05:00"
  },
  {
    "name": "Pugh Cote",
    "city": "ZIDANT",
    "joined": "2014-10-30T06:55:42 +05:00"
  },
  {
    "name": "Toni Nicholson",
    "city": "HOUSEDOWN",
    "joined": "2015-03-16T05:29:57 +05:00"
  },
  {
    "name": "Terri Wilkerson",
    "city": "AQUACINE",
    "joined": "2014-05-23T11:12:03 +05:00"
  },
  {
    "name": "Hopper Shields",
    "city": "COWTOWN",
    "joined": "2015-04-27T08:17:32 +05:00"
  },
  {
    "name": "Gabrielle Ingram",
    "city": "BITREX",
    "joined": "2014-10-25T03:10:05 +05:00"
  },
  {
    "name": "Navarro Moreno",
    "city": "KEGULAR",
    "joined": "2015-08-31T07:48:27 +05:00"
  },
  {
    "name": "Maryellen Miles",
    "city": "ANARCO",
    "joined": "2014-01-08T12:00:55 +05:00"
  },
  {
    "name": "Elizabeth Crane",
    "city": "LETPRO",
    "joined": "2014-08-02T10:37:52 +05:00"
  },
  {
    "name": "Pierce Serrano",
    "city": "UNQ",
    "joined": "2015-04-13T03:33:14 +05:00"
  },
  {
    "name": "Nanette Kidd",
    "city": "LUDAK",
    "joined": "2015-07-23T05:00:25 +05:00"
  },
  {
    "name": "Luella Roberts",
    "city": "ZOSIS",
    "joined": "2015-07-17T03:02:29 +05:00"
  },
  {
    "name": "Marie Goff",
    "city": "ZILLA",
    "joined": "2014-08-17T01:25:21 +05:00"
  },
  {
    "name": "Terrie Mcmahon",
    "city": "ZOLAR",
    "joined": "2015-06-10T04:33:05 +05:00"
  },
  {
    "name": "Mercer Daniels",
    "city": "COMBOGEN",
    "joined": "2014-02-28T05:25:20 +05:00"
  },
  {
    "name": "Daisy Duran",
    "city": "TECHMANIA",
    "joined": "2014-05-03T06:35:20 +05:00"
  },
  {
    "name": "Kate Mcdaniel",
    "city": "SOLAREN",
    "joined": "2015-05-27T12:40:05 +05:00"
  },
  {
    "name": "Leigh Riddle",
    "city": "ENOMEN",
    "joined": "2014-04-16T05:11:04 +05:00"
  },
  {
    "name": "Mayo Rice",
    "city": "VANTAGE",
    "joined": "2014-02-13T07:43:19 +05:00"
  },
  {
    "name": "Penelope Crosby",
    "city": "BULLZONE",
    "joined": "2014-01-24T11:05:58 +05:00"
  },
  {
    "name": "Campbell Whitehead",
    "city": "AVENETRO",
    "joined": "2014-06-24T08:02:21 +05:00"
  },
  {
    "name": "Candy Delaney",
    "city": "BILLMED",
    "joined": "2015-01-04T01:13:39 +05:00"
  },
  {
    "name": "Dina Christian",
    "city": "INQUALA",
    "joined": "2015-04-30T01:05:47 +05:00"
  },
  {
    "name": "Agnes Fernandez",
    "city": "KROG",
    "joined": "2014-08-25T12:09:42 +05:00"
  },
  {
    "name": "Hendrix Washington",
    "city": "EMPIRICA",
    "joined": "2014-09-14T06:10:06 +05:00"
  },
  {
    "name": "Simmons Maddox",
    "city": "PURIA",
    "joined": "2014-01-14T04:54:38 +05:00"
  },
  {
    "name": "Fuentes Mccoy",
    "city": "ILLUMITY",
    "joined": "2015-03-07T12:45:14 +05:00"
  },
  {
    "name": "Jenny Curry",
    "city": "ORGANICA",
    "joined": "2014-10-22T10:54:37 +05:00"
  },
  {
    "name": "Cantu Galloway",
    "city": "OPTICALL",
    "joined": "2014-02-06T07:33:05 +05:00"
  }
]}
